pypinger/__init__.py
pypinger/pypinger.py
pypinger-2.0.3.dist-info/LICENSE
pypinger-2.0.3.dist-info/METADATA
pypinger-2.0.3.dist-info/WHEEL
pypinger-2.0.3.dist-info/entry_points.txt
pypinger-2.0.3.dist-info/top_level.txt
pypinger-2.0.3.dist-info/RECORD
