Metadata-Version: 2.1
Name: pypinger
Version: 2.0.3
Summary: Another way to ping in Python
Home-page: https://github.com/DataKnox/pypinger
Author: Knox Hutchinson
Author-email: knox@knoxsdata.com
License: MIT
Keywords: ping,icmp,network
Platform: UNKNOWN
Classifier: Development Status :: 5 - Production/Stable
Classifier: Intended Audience :: System Administrators
Classifier: Natural Language :: English
